{
	"id": "4deae221-8958-4607-b514-691ad312b043",
	"name": "OAuth 2.0",
	"values": [
		{
			"key": "client_id",
			"value": "",
			"enabled": true
		},
		{
			"key": "client_secret",
			"value": "",
			"enabled": true
		},
		{
			"key": "refresh_token",
			"value": "",
			"enabled": true
		},
		{
			"key": "access_token",
			"value": "",
			"enabled": true
		},
		{
			"key": "xero-tenant-id",
			"value": "",
			"enabled": true
		},
		{
			"key": "re_directURI",
			"value": "",
			"enabled": true
		},
		{
			"key": "scopes",
			"value": "",
			"enabled": true
		},
		{
			"key": "state",
			"value": "",
			"enabled": true
		}
	],
	"_postman_variable_scope": "environment",
	"_postman_exported_at": "2019-11-07T13:46:19.270Z",
	"_postman_exported_using": "Postman/7.10.0"
}